dynamic_logger/.gitignore
dynamic_logger/LICENSE
dynamic_logger/__init__.py
dynamic_logger/examples/example.py
dynamic_logger-1.0.2.dist-info/WHEEL
dynamic_logger-1.0.2.dist-info/METADATA
dynamic_logger-1.0.2.dist-info/RECORD
