Metadata-Version: 2.1
Name: dynamic-logger
Version: 1.0.2
Summary: Dynamic Logger Class for logging
Home-page: https://github.com/ajatkj/dynamic_logger
License: MIT
Keywords: logging,extra_logging,dynamic_logging
Author: ajatkj
Author-email: ajatkj@yahoo.co.in
Requires-Python: >=3.10,<4.0
Classifier: License :: OSI Approved :: MIT License
Classifier: Programming Language :: Python :: 3
Classifier: Programming Language :: Python :: 3.10
Project-URL: Repository, https://github.com/ajatkj/dynamic_logger
